freshbooks_mcp/__init__.py
freshbooks_mcp_server-0.1.0.dist-info/METADATA
freshbooks_mcp_server-0.1.0.dist-info/WHEEL
freshbooks_mcp_server-0.1.0.dist-info/entry_points.txt
freshbooks_mcp_server-0.1.0.dist-info/RECORD
